wa_automation/__init__.py
wa_automation/core.py
wa_automation/exceptions.py
wa_automation-0.1.3.dist-info/METADATA
wa_automation-0.1.3.dist-info/WHEEL
wa_automation-0.1.3.dist-info/licenses/LICENSE
wa_automation-0.1.3.dist-info/RECORD
