Metadata-Version: 2.4
Name: wa-automation
Version: 0.1.3
Summary: A Python library for WhatsApp Web automation
Project-URL: Homepage, https://github.com/RahulBarakoti-programming/wa-automation
Project-URL: Issues, https://github.com/RahulBarakoti-programming/wa-automation/issues
Author-email: Rahul Barakoti <rahulbarakoti5@gmail.com>
License-File: LICENSE
Classifier: Development Status :: 3 - Alpha
Classifier: Intended Audience :: Developers
Classifier: License :: OSI Approved :: MIT License
Classifier: Programming Language :: Python :: 3
Classifier: Programming Language :: Python :: 3.8
Classifier: Programming Language :: Python :: 3.9
Classifier: Programming Language :: Python :: 3.10
Classifier: Programming Language :: Python :: 3.11
Requires-Python: >=3.8
Requires-Dist: selenium>=4.0.0
Requires-Dist: webdriver-manager>=3.8.0
